easyuse_nacos/__init__.py
easyuse_nacos/easyuse_nacos.py
easyuse_nacos-0.0.3.1.dist-info/LICENSE
easyuse_nacos-0.0.3.1.dist-info/METADATA
easyuse_nacos-0.0.3.1.dist-info/WHEEL
easyuse_nacos-0.0.3.1.dist-info/top_level.txt
easyuse_nacos-0.0.3.1.dist-info/RECORD
