Metadata-Version: 2.1
Name: easyuse-nacos
Version: 0.0.3.1
Summary: A user-friendly wrapper around the nacos-sdk-python package
Author-email: zhangxiaojia <47974937@qq.com>
Project-URL: Homepage, https://zhangxiaojiawow.github.io/easyuse_nacos/
Project-URL: github, https://github.com/zhangxiaojiawow/easyuse_nacos
Project-URL: Issues, https://github.com/zhangxiaojiawow/easyuse_nacos/issues
Classifier: Programming Language :: Python :: 3
Classifier: License :: OSI Approved :: MIT License
Classifier: Operating System :: OS Independent
Requires-Python: >=3.8
License-File: LICENSE
Requires-Dist: nacos-sdk-python
